andersen_ev/__init__.py
andersen_ev/andersen.py
andersen_ev/auth.py
andersen_ev/mobile.py
andersen_ev/schema/andersen.graphql
andersen_ev-0.1.4.dist-info/LICENCE
andersen_ev-0.1.4.dist-info/METADATA
andersen_ev-0.1.4.dist-info/WHEEL
andersen_ev-0.1.4.dist-info/top_level.txt
andersen_ev-0.1.4.dist-info/RECORD
