Metadata-Version: 2.1
Name: andersen-ev
Version: 0.1.4
Summary: Python package for controlling the Andersen A2 EV charger
Author: James Brown
License: MIT
Project-URL: Homepage, https://github.com/strobejb/andersen-ev
Project-URL: Bug Tracker, https://github.com/strobejb/andersen-ev/issues
Classifier: Programming Language :: Python :: 3
Classifier: License :: OSI Approved :: MIT License
Classifier: Operating System :: OS Independent
Requires-Python: >=3.7
License-File: LICENCE
